datasketch/__init__.py
datasketch/b_bit_minhash.py
datasketch/hashfunc.py
datasketch/hnsw.py
datasketch/hyperloglog.py
datasketch/hyperloglog_const.py
datasketch/lean_minhash.py
datasketch/lsh.py
datasketch/lsh_bloom.py
datasketch/lshensemble.py
datasketch/lshensemble_partition.py
datasketch/lshforest.py
datasketch/minhash.py
datasketch/storage.py
datasketch/weighted_minhash.py
datasketch/experimental/__init__.py
datasketch/experimental/aio/__init__.py
datasketch/experimental/aio/lsh.py
datasketch/experimental/aio/storage.py
datasketch-1.9.0.dist-info/METADATA
datasketch-1.9.0.dist-info/WHEEL
datasketch-1.9.0.dist-info/licenses/LICENSE
datasketch-1.9.0.dist-info/RECORD
