Metadata-Version: 2.4
Name: datasketch
Version: 1.9.0
Summary: Probabilistic data structures for processing and searching very large datasets
Project-URL: Homepage, https://ekzhu.github.io/datasketch
Project-URL: Bug Tracker, https://github.com/ekzhu/datasketch/issues
Project-URL: Documentation, https://ekzhu.github.io/datasketch
Project-URL: Source, https://github.com/ekzhu/datasketch
Author-email: ekzhu <ekzhu@cs.toronto.edu>
License: MIT
License-File: LICENSE
Keywords: database,datamining
Classifier: Development Status :: 5 - Production/Stable
Classifier: Intended Audience :: Developers
Classifier: License :: OSI Approved :: MIT License
Classifier: Programming Language :: Python :: 3.9
Classifier: Programming Language :: Python :: 3.10
Classifier: Programming Language :: Python :: 3.11
Classifier: Programming Language :: Python :: 3.12
Classifier: Programming Language :: Python :: 3.13
Classifier: Topic :: Database
Classifier: Topic :: Scientific/Engineering :: Information Analysis
Requires-Python: >=3.9
Requires-Dist: numpy>=1.11
Requires-Dist: scipy>=1.0.0
Provides-Extra: benchmark
Requires-Dist: matplotlib>=3.1.2; extra == 'benchmark'
Requires-Dist: nltk>=3.4.5; extra == 'benchmark'
Requires-Dist: pandas>=0.25.3; extra == 'benchmark'
Requires-Dist: pyfarmhash>=0.2.2; extra == 'benchmark'
Requires-Dist: pyhash>=0.9.3; extra == 'benchmark'
Requires-Dist: scikit-learn>=0.21.3; extra == 'benchmark'
Requires-Dist: scipy>=1.3.3; extra == 'benchmark'
Requires-Dist: setsimilaritysearch>=0.1.7; extra == 'benchmark'
Provides-Extra: bloom
Requires-Dist: pybloomfilter3>=0.7.2; extra == 'bloom'
Provides-Extra: cassandra
Requires-Dist: cassandra-driver>=3.20; extra == 'cassandra'
Provides-Extra: experimental-aio
Requires-Dist: aiounittest; extra == 'experimental-aio'
Requires-Dist: motor>3.6.0; extra == 'experimental-aio'
Provides-Extra: redis
Requires-Dist: redis>=2.10.0; extra == 'redis'
Provides-Extra: test
Requires-Dist: cassandra-driver>=3.20; extra == 'test'
Requires-Dist: coverage; extra == 'test'
Requires-Dist: mock>=2.0.0; extra == 'test'
Requires-Dist: mockredispy; extra == 'test'
Requires-Dist: nose-exclude>=0.5.0; extra == 'test'
Requires-Dist: nose>=1.3.7; extra == 'test'
Requires-Dist: pymongo>=3.9.0; extra == 'test'
Requires-Dist: pytest; extra == 'test'
Requires-Dist: pytest-asyncio; extra == 'test'
Requires-Dist: pytest-cov; extra == 'test'
Requires-Dist: pytest-rerunfailures; extra == 'test'
Requires-Dist: redis>=2.10.0; extra == 'test'
